nss/__init__.py
nss/deprecations.py
nss/error.cpython-314-x86_64-linux-gnu.so
nss/io.cpython-314-x86_64-linux-gnu.so
nss/io.pyi
nss/nss.cpython-314-x86_64-linux-gnu.so
nss/nss.pyi
nss/nss_context.py
nss/secure_logging.py
nss/ssl.cpython-314-x86_64-linux-gnu.so
nss/ssl.pyi
python_nss_ng.libs/libnspr4-1fcb4d2c.so
python_nss_ng.libs/libnss3-2baffc3b.so
python_nss_ng.libs/libnssutil3-9d74f7c3.so
python_nss_ng.libs/libplc4-9acef6e7.so
python_nss_ng.libs/libplds4-a10766a7.so
python_nss_ng.libs/libsmime3-81b2c893.so
python_nss_ng.libs/libssl3-848e5dd7.so
python_nss_ng-1.0.4.dist-info/METADATA
python_nss_ng-1.0.4.dist-info/WHEEL
python_nss_ng-1.0.4.dist-info/RECORD
python_nss_ng-1.0.4.dist-info/licenses/LICENSE
python_nss_ng-1.0.4.dist-info/licenses/LICENSES/MPL-2.0.txt
