Metadata-Version: 2.4
Name: python-nss-ng
Version: 1.0.4
Summary: Python bindings for Network Security Services (NSS) and Netscape Portable Runtime (NSPR)
Keywords: nss,nspr,cryptography,ssl,tls,pki,x509,security
Author-Email: John Dennis <jdennis@redhat.com>, Matthew Watkins <mwatkins@linuxfoundation.org>
Maintainer-Email: Matthew Watkins <mwatkins@linuxfoundation.org>
License-Expression: MPL-2.0 OR GPL-2.0-or-later OR LGPL-2.0-or-later
License-File: LICENSE
License-File: LICENSES/MPL-2.0.txt
Classifier: Development Status :: 5 - Production/Stable
Classifier: Intended Audience :: Developers
Classifier: Operating System :: POSIX
Classifier: Operating System :: POSIX :: Linux
Classifier: Operating System :: MacOS
Classifier: Programming Language :: C
Classifier: Programming Language :: Python :: 3
Classifier: Programming Language :: Python :: 3.10
Classifier: Programming Language :: Python :: 3.11
Classifier: Programming Language :: Python :: 3.12
Classifier: Programming Language :: Python :: 3.13
Classifier: Programming Language :: Python :: 3.14
Classifier: Programming Language :: Python :: Implementation :: CPython
Classifier: Topic :: Security
Classifier: Topic :: Security :: Cryptography
Classifier: Topic :: Software Development :: Libraries :: Python Modules
Project-URL: Homepage, http://www.mozilla.org/projects/security/pki/python-nss-ng
Project-URL: Documentation, http://www.mozilla.org/projects/security/pki/python-nss-ng
Project-URL: Repository, https://github.com/ModeSevenIndustrialSolutions/python-nss-ng
Project-URL: Issues, https://github.com/ModeSevenIndustrialSolutions/python-nss-ng/issues
Requires-Python: >=3.10
Provides-Extra: test
Requires-Dist: pytest>=9.0.2; extra == "test"
Requires-Dist: pytest-cov>=7.0.0; extra == "test"
Requires-Dist: coverage[toml]>=7.13.1; extra == "test"
Requires-Dist: pytest-xdist>=3.8.0; extra == "test"
Requires-Dist: mypy>=1.0.0; extra == "test"
Requires-Dist: hypothesis>=6.0.0; extra == "test"
Requires-Dist: mutmut>=2.4.0; extra == "test"
Requires-Dist: meson>=1.10.0; extra == "test"
Requires-Dist: meson-python>=0.18.0; extra == "test"
Requires-Dist: ninja; extra == "test"
Provides-Extra: dev
Requires-Dist: pytest>=9.0.2; extra == "dev"
Requires-Dist: pytest-cov>=7.0.0; extra == "dev"
Requires-Dist: coverage[toml]>=7.13.1; extra == "dev"
Requires-Dist: pytest-xdist>=3.8.0; extra == "dev"
Requires-Dist: mypy>=1.0.0; extra == "dev"
Requires-Dist: hypothesis>=6.0.0; extra == "dev"
Requires-Dist: mutmut>=2.4.0; extra == "dev"
Requires-Dist: ruff>=0.14.10; extra == "dev"
Requires-Dist: build>=1.3.0; extra == "dev"
Requires-Dist: meson>=1.10.0; extra == "dev"
Requires-Dist: meson-python>=0.18.0; extra == "dev"
Requires-Dist: ninja; extra == "dev"
